pyth/__init__.py
pyth/__main__.py
pyth/helper.py
pyth/template.py
pyth/utils.py
pyth/version.py
supersk_pyth-0.1.0.dist-info/LICENSE
supersk_pyth-0.1.0.dist-info/METADATA
supersk_pyth-0.1.0.dist-info/WHEEL
supersk_pyth-0.1.0.dist-info/entry_points.txt
supersk_pyth-0.1.0.dist-info/top_level.txt
supersk_pyth-0.1.0.dist-info/RECORD
