Metadata-Version: 2.1
Name: supersk-pyth
Version: 0.1.0
Summary: Simple Jinja2 Template Wrapper
Home-page: https://gitlab.com/supersk-python/pyth
Author: super-sk
License: MIT
Project-URL: Code, https://gitlab.com/supersk-python/pyth
Project-URL: Issues, https://gitlab.com/supersk-python/pyth/-/issues
Project-URL: Documentation, https://supersk-python.gitlab.io/pyth
Keywords: template,utility
Platform: Linux
Classifier: Development Status :: 3 - Alpha
Classifier: Intended Audience :: Developers
Classifier: Intended Audience :: System Administrators
Classifier: License :: OSI Approved :: MIT License
Classifier: Programming Language :: Python :: 3
Classifier: Programming Language :: Python :: 3.6
Classifier: Topic :: Software Development
Classifier: Topic :: Software Development :: Libraries :: Python Modules
Classifier: Topic :: Text Processing
Classifier: Topic :: Utilities
Requires-Python: >=3.6
Requires-Dist: jinja2 (==2.11.2)
